napari_deepmeta/__init__.py
napari_deepmeta/_version.py
napari_deepmeta/_widget.py
napari_deepmeta/deepmeta_functions.py
napari_deepmeta/models.py
napari_deepmeta/napari.yaml
napari_deepmeta/_tests/__init__.py
napari_deepmeta/_tests/test_widget.py
napari_deepmeta/resources/model.pth
napari_deepmeta/resources/souris_8.tif
napari_deepmeta-2.1.dist-info/LICENSE
napari_deepmeta-2.1.dist-info/METADATA
napari_deepmeta-2.1.dist-info/WHEEL
napari_deepmeta-2.1.dist-info/entry_points.txt
napari_deepmeta-2.1.dist-info/top_level.txt
napari_deepmeta-2.1.dist-info/RECORD
