Metadata-Version: 2.1
Name: napari-deepmeta
Version: 2.1
Summary: Mice lungs and metastases segmentation tool.
Home-page: https://github.com/EdgarLefevre/napari-deepmeta
Author: Edgar Lefevre
Author-email: lefevreedg@gmail.com
License: MIT
Project-URL: Bug Tracker, https://github.com/EdgarLefevre/napari-deepmeta/issues
Project-URL: Documentation, https://github.com/EdgarLefevre/napari-deepmeta#README.md
Project-URL: Source Code, https://github.com/EdgarLefevre/napari-deepmeta
Project-URL: User Support, https://github.com/EdgarLefevre/napari-deepmeta/issues
Classifier: Development Status :: 2 - Pre-Alpha
Classifier: Framework :: napari
Classifier: Intended Audience :: Developers
Classifier: License :: OSI Approved :: MIT License
Classifier: Operating System :: OS Independent
Classifier: Programming Language :: Python
Classifier: Programming Language :: Python :: 3
Classifier: Programming Language :: Python :: 3 :: Only
Classifier: Programming Language :: Python :: 3.8
Classifier: Programming Language :: Python :: 3.9
Classifier: Programming Language :: Python :: 3.10
Classifier: Topic :: Software Development :: Testing
Requires-Python: >=3.8
License-File: LICENSE
Requires-Dist: connected-components-3d
Requires-Dist: magicgui
Requires-Dist: napari
Requires-Dist: numpy
Requires-Dist: opencv-python
Requires-Dist: qtpy
Requires-Dist: scikit-image
Requires-Dist: torch
Provides-Extra: testing
Requires-Dist: connected-components-3d ; extra == 'testing'
Requires-Dist: napari ; extra == 'testing'
Requires-Dist: opencv-python ; extra == 'testing'
Requires-Dist: pyqt5 ; extra == 'testing'
Requires-Dist: pytest ; extra == 'testing'
Requires-Dist: pytest-cov ; extra == 'testing'
Requires-Dist: pytest-qt ; extra == 'testing'
Requires-Dist: tox ; extra == 'testing'
